README.md
packmodule.py
setup.py
packmodule.egg-info/PKG-INFO
packmodule.egg-info/SOURCES.txt
packmodule.egg-info/dependency_links.txt
packmodule.egg-info/top_level.txt