Metadata-Version: 2.1
Name: packmodule
Version: 1.0.0
Summary: Python code packer for CloudFormation
Home-page: https://github.com/schlarpc/packmodule
License: UNKNOWN
Platform: UNKNOWN
